NCaptcha/__init__.py
NCaptcha/main.py
ncaptcha_python-0.0.3.dist-info/licenses/LICENSE
ncaptcha_python-0.0.3.dist-info/METADATA
ncaptcha_python-0.0.3.dist-info/WHEEL
ncaptcha_python-0.0.3.dist-info/top_level.txt
ncaptcha_python-0.0.3.dist-info/RECORD
