Metadata-Version: 2.4
Name: NCaptcha-python
Version: 0.0.3
Summary: Simple Captcha
Author-email: namo <kdevnamo@gmail.com>
License-Expression: MIT
Project-URL: Homepage, https://github.com/dev-namo/NCaptcha-python
Project-URL: Issues, https://github.com/dev-namo/NCaptcha-python/issues
Classifier: Programming Language :: Python :: 3
Classifier: Operating System :: OS Independent
Requires-Python: >=3.9
License-File: LICENSE
Dynamic: license-file
